LICENSE
MANIFEST.in
README.rst
setup.py
django_embedded_media.egg-info/PKG-INFO
django_embedded_media.egg-info/SOURCES.txt
django_embedded_media.egg-info/dependency_links.txt
django_embedded_media.egg-info/not-zip-safe
django_embedded_media.egg-info/top_level.txt
embedded_media/__init__.py
embedded_media/media.py
embedded_media/models.py
embedded_media/tests.py