Metadata-Version: 1.1
Name: django-embedded-media
Version: 0.1.0
Summary: Render inline CSS and JS in Django forms media.
Home-page: https://github.com/dmpayton/django-embedded-media
Author: Derek Payton
Author-email: derek.payton@gmail.com
License: MIT License
Download-URL: https://github.com/dmpayton/django-embedded-media/tarball/v0.1.0
Keywords: django media
Platform: UNKNOWN
Classifier: Development Status :: 4 - Beta
Classifier: Framework :: Django
Classifier: Intended Audience :: Developers
Classifier: License :: OSI Approved :: MIT License
Classifier: Natural Language :: English
Classifier: Operating System :: OS Independent
Classifier: Programming Language :: Python
Classifier: Topic :: Internet :: WWW/HTTP :: Dynamic Content
